[
  {
    "place_id": "event_001",
    "name": "夏のキッズアートワークショップ〜ガラス絵の具で世界に一枚だけのうちわ作り〜",
    "address": "東京都渋谷区神南1-19-8 渋谷文化総合センター大和田 3F",
    "website": "https://peatix.com/",
    "phone": "",
    "rating": null,
    "review_count": 18,
    "summary": "ガラス絵の具を使って、オリジナルのうちわを作ります。3歳から参加OK、材料費込みです。",
    "types": ["event"],
    "lat": 35.6618, "lng": 139.6989,
    "search_keyword": "アート",
    "has_photos": false, "photo_refs": [], "reviews": [],
    "source": "event",
    "event_display": "7/5（土） 10:00〜12:00",
    "event_datetime": "2026-07-05T10:00:00+09:00",
    "event_capacity": 20, "event_remaining": 6,
    "organizer": "東京キッズアートラボ"
  },
  {
    "place_id": "event_002",
    "name": "夏休み特別！子ども科学実験教室〜光と色の不思議〜",
    "address": "東京都新宿区西新宿2-8-1 都庁第一本庁舎 45Fイベントホール",
    "website": "https://connpass.com/",
    "phone": "",
    "rating": null,
    "review_count": 34,
    "summary": "光の屈折・プリズム・色の混合など「光と色」をテーマにした科学実験。小学生対象、保護者同伴OK。",
    "types": ["event"],
    "lat": 35.6896, "lng": 139.6917,
    "search_keyword": "科学",
    "has_photos": false, "photo_refs": [], "reviews": [],
    "source": "event",
    "event_display": "7/12（日） 13:00〜15:00",
    "event_datetime": "2026-07-12T13:00:00+09:00",
    "event_capacity": 30, "event_remaining": 12,
    "organizer": "東京サイエンスキッズ"
  },
  {
    "place_id": "event_003",
    "name": "親子クッキング体験〜夏野菜とチーズのオリジナルピザを作ろう〜",
    "address": "東京都港区南青山3-10-10 青山コミュニティキッチン",
    "website": "https://peatix.com/",
    "phone": "",
    "rating": null,
    "review_count": 22,
    "summary": "旬の夏野菜を使ったピザ作り体験。生地こねから焼き上げまで親子で挑戦！アレルギー対応あり。",
    "types": ["event"],
    "lat": 35.6674, "lng": 139.7195,
    "search_keyword": "料理",
    "has_photos": false, "photo_refs": [], "reviews": [],
    "source": "event",
    "event_display": "7/6（日） 11:00〜13:30",
    "event_datetime": "2026-07-06T11:00:00+09:00",
    "event_capacity": 16, "event_remaining": 4,
    "organizer": "青山ファミリーキッチン"
  },
  {
    "place_id": "event_004",
    "name": "小学生のためのゲームプログラミング体験〜Scratchでオリジナルゲームを作ろう〜",
    "address": "東京都千代田区神田小川町3-28 TKP神田ビジネスセンター",
    "website": "https://connpass.com/",
    "phone": "",
    "rating": null,
    "review_count": 45,
    "summary": "Scratchで自分だけのゲームを作る体験。初心者OK、PCはこちらで用意。小学2〜6年生対象。",
    "types": ["event"],
    "lat": 35.6954, "lng": 139.7627,
    "search_keyword": "プログラミング",
    "has_photos": false, "photo_refs": [], "reviews": [],
    "source": "event",
    "event_display": "7/19（日） 10:00〜12:00",
    "event_datetime": "2026-07-19T10:00:00+09:00",
    "event_capacity": 24, "event_remaining": 9,
    "organizer": "CoderDojo Tokyo"
  },
  {
    "place_id": "event_005",
    "name": "夏の里山体験！カブトムシと野菜の収穫〜都内で自然体験〜",
    "address": "東京都世田谷区大蔵4-1-1 砧公園 野外ステージ前",
    "website": "https://peatix.com/",
    "phone": "",
    "rating": null,
    "review_count": 28,
    "summary": "都内でカブトムシ探しと夏野菜の収穫体験。3歳から参加OK。収穫した野菜は持ち帰れます。",
    "types": ["event"],
    "lat": 35.6313, "lng": 139.6067,
    "search_keyword": "自然",
    "has_photos": false, "photo_refs": [], "reviews": [],
    "source": "event",
    "event_display": "7/13（日） 9:00〜11:30",
    "event_datetime": "2026-07-13T09:00:00+09:00",
    "event_capacity": 20, "event_remaining": 7,
    "organizer": "東京里山プロジェクト"
  },
  {
    "place_id": "event_006",
    "name": "キッズ音楽ワークショップ〜身近な素材で楽器を作って演奏しよう〜",
    "address": "東京都目黒区目黒2-10-11 目黒区民センター 小ホール",
    "website": "https://peatix.com/",
    "phone": "",
    "rating": null,
    "review_count": 15,
    "summary": "ペットボトルや空き缶で手作り楽器を制作し、みんなで合奏！音楽未経験でも大歓迎。4歳以上対象。",
    "types": ["event"],
    "lat": 35.6334, "lng": 139.7153,
    "search_keyword": "音楽",
    "has_photos": false, "photo_refs": [], "reviews": [],
    "source": "event",
    "event_display": "7/20（月・祝） 14:00〜16:00",
    "event_datetime": "2026-07-20T14:00:00+09:00",
    "event_capacity": 18, "event_remaining": 3,
    "organizer": "目黒ミュージックラボ"
  },
  {
    "place_id": "event_007",
    "name": "粘土でつくろう！キッズ陶芸体験教室〜夏の一日クラス〜",
    "address": "東京都荒川区西日暮里5-38-13 陶芸工房 土と炎",
    "website": "https://peatix.com/",
    "phone": "",
    "rating": null,
    "review_count": 11,
    "summary": "本格的なろくろと手びねり両方を体験できる一日陶芸教室。作品は後日焼成・郵送します。5歳以上対象。",
    "types": ["event"],
    "lat": 35.7319, "lng": 139.7698,
    "search_keyword": "工作",
    "has_photos": false, "photo_refs": [], "reviews": [],
    "source": "event",
    "event_display": "8/2（日） 10:00〜13:00",
    "event_datetime": "2026-08-02T10:00:00+09:00",
    "event_capacity": 12, "event_remaining": 5,
    "organizer": "土と炎 陶芸工房"
  },
  {
    "place_id": "event_008",
    "name": "親子で学ぶSDGs工作教室〜廃材アートでエコバッグを作ろう〜",
    "address": "東京都杉並区高円寺北2-1-2 高円寺地域区民センター 2F",
    "website": "https://peatix.com/",
    "phone": "",
    "rating": null,
    "review_count": 9,
    "summary": "廃材を使ったアップサイクルアートに挑戦！エコバッグにスタンプ・貼り付けでオリジナル作品を作ります。3歳〜小学生対象。",
    "types": ["event"],
    "lat": 35.7070, "lng": 139.6494,
    "search_keyword": "アート",
    "has_photos": false, "photo_refs": [], "reviews": [],
    "source": "event",
    "event_display": "7/27（日） 13:00〜15:00",
    "event_datetime": "2026-07-27T13:00:00+09:00",
    "event_capacity": 15, "event_remaining": 8,
    "organizer": "高円寺エコキッズクラブ"
  }
]
